deployment/matmul.so
deployment/matmul.c
deployment/__init__.py
deployment/_version.py
deployment/deploy.py
python_deployment-0.0.1.dist-info/WHEEL
python_deployment-0.0.1.dist-info/top_level.txt
python_deployment-0.0.1.dist-info/METADATA
python_deployment-0.0.1.dist-info/RECORD
