Metadata-Version: 2.1
Name: python-deployment
Version: 0.0.1
Summary: Python Deployment
Home-page: https://github.com/LSchueler/Python-Deployment
Author: Lennart Schueler
Author-email: mostem@posteo.org
Maintainer: Lennart Schueler
Maintainer-email: mostem@posteo.org
License: GPL -  see LICENSE
Platform: Windows
Platform: Linux
Platform: Solaris
Platform: Mac OS-X
Platform: Unix
Classifier: Development Status :: 5 - Production/Stable
Classifier: Intended Audience :: Developers
Classifier: License :: OSI Approved :: GNU General Public License v3 (GPLv3)
Classifier: Natural Language :: English
Classifier: Operating System :: Unix
Classifier: Programming Language :: Python
Classifier: Programming Language :: Python :: 3
Classifier: Topic :: Utilities
Requires-Dist: numpy (>=1.14.5)
